{
   "belongs_to" : {
      "fetch" : 0
   },
   "has_many" : {
      "fetch" : 0
   },
   "might_have" : {
      "fetch" : 0
   },
   "sets" : [
      {
         "quantity" : "all",
         "class" : "Topic"
      },
      {
         "quantity" : "all",
         "class" : "ViewLayout"
      },
      {
         "quantity" : "all",
         "class" : "Intgr"
      },
      {
         "class" : "Current",
         "quantity" : "all"
      },
      {
         "class" : "FileOption",
         "quantity" : "all"
      },
      {
         "quantity" : "all",
         "class" : "Person"
      },
      {
         "class" : "Submission",
         "quantity" : "all"
      },
      {
         "class" : "AlertSend",
         "quantity" : "all"
      },
      {
         "class" : "Title",
         "quantity" : "all"
      },
      {
         "quantity" : "all",
         "class" : "AlertColumn"
      },
      {
         "quantity" : "all",
         "class" : "Dashboard"
      },
      {
         "class" : "Filter",
         "quantity" : "all"
      },
      {
         "quantity" : "all",
         "class" : "InstanceGroup"
      },
      {
         "quantity" : "all",
         "class" : "Organisation"
      },
      {
         "class" : "CurvalField",
         "quantity" : "all"
      },
      {
         "quantity" : "all",
         "class" : "Alert"
      },
      {
         "class" : "Import",
         "quantity" : "all"
      },
      {
         "class" : "ImportRow",
         "quantity" : "all"
      },
      {
         "quantity" : "all",
         "class" : "View"
      },
      {
         "quantity" : "all",
         "class" : "Export"
      },
      {
         "quantity" : "all",
         "class" : "Curval"
      },
      {
         "quantity" : "all",
         "class" : "Widget"
      },
      {
         "quantity" : "all",
         "class" : "Instance"
      },
      {
         "quantity" : "all",
         "class" : "DisplayField"
      },
      {
         "quantity" : "all",
         "class" : "Permission"
      },
      {
         "class" : "GraphColor",
         "quantity" : "all"
      },
      {
         "quantity" : "all",
         "class" : "Oauthtoken"
      },
      {
         "class" : "ViewGroup",
         "quantity" : "all"
      },
      {
         "quantity" : "all",
         "class" : "Layout"
      },
      {
         "quantity" : "all",
         "class" : "MetricGroup"
      },
      {
         "class" : "Sort",
         "quantity" : "all"
      },
      {
         "quantity" : "all",
         "class" : "Team"
      },
      {
         "class" : "LayoutGroup",
         "quantity" : "all"
      },
      {
         "quantity" : "all",
         "class" : "Metric"
      },
      {
         "quantity" : "all",
         "class" : "UserLastrecord"
      },
      {
         "class" : "UserGraph",
         "quantity" : "all"
      },
      {
         "quantity" : "all",
         "class" : "Enumval"
      },
      {
         "class" : "Ragval",
         "quantity" : "all"
      },
      {
         "quantity" : "all",
         "class" : "Record"
      },
      {
         "quantity" : "all",
         "class" : "Daterange"
      },
      {
         "quantity" : "all",
         "class" : "AlertCache"
      },
      {
         "quantity" : "all",
         "class" : "Oauthclient"
      },
      {
         "quantity" : "all",
         "class" : "UserPermission"
      },
      {
         "class" : "String",
         "quantity" : "all"
      },
      {
         "quantity" : "all",
         "class" : "LayoutDepend"
      },
      {
         "quantity" : "all",
         "class" : "Rag"
      },
      {
         "quantity" : "all",
         "class" : "Graph"
      },
      {
         "class" : "Department",
         "quantity" : "all"
      },
      {
         "quantity" : "all",
         "class" : "FilteredValue"
      },
      {
         "quantity" : "all",
         "class" : "Site"
      },
      {
         "class" : "Fileval",
         "quantity" : "all"
      },
      {
         "quantity" : "all",
         "class" : "Calc"
      },
      {
         "quantity" : "all",
         "class" : "Date"
      },
      {
         "class" : "Group",
         "quantity" : "all"
      },
      {
         "class" : "User",
         "quantity" : "all"
      },
      {
         "class" : "Enum",
         "quantity" : "all"
      },
      {
         "quantity" : "all",
         "class" : "ViewLimit"
      },
      {
         "class" : "File",
         "quantity" : "all"
      },
      {
         "class" : "Changed",
         "quantity" : "all"
      },
      {
         "quantity" : "all",
         "class" : "Audit"
      },
      {
         "quantity" : "all",
         "class" : "Calcval"
      },
      {
         "quantity" : "all",
         "class" : "UserGroup"
      }
   ]
}
